ABOUT.txt
CHANGES.txt
COPYRIGHT.txt
LICENSE.txt
MANIFEST.in
README.txt
index.txt
setup.py
tt/__init__.py
tt.eggdeps.egg-info/PKG-INFO
tt.eggdeps.egg-info/SOURCES.txt
tt.eggdeps.egg-info/dependency_links.txt
tt.eggdeps.egg-info/entry_points.txt
tt.eggdeps.egg-info/namespace_packages.txt
tt.eggdeps.egg-info/not-zip-safe
tt.eggdeps.egg-info/requires.txt
tt.eggdeps.egg-info/top_level.txt
tt/eggdeps/__init__.py
tt/eggdeps/cli.py
tt/eggdeps/dot.py
tt/eggdeps/graph.py
tt/eggdeps/plaintext.py
tt/eggdeps/requirements.py
tt/eggdeps/tests.py
tt/eggdeps/utils.py
tt/eggdeps/django/__init__.py
tt/eggdeps/django/urls.py
tt/eggdeps/django/views.py