Metadata-Version: 1.1
Name: tt.eggdeps
Version: 0.5a1
Summary: Compute a dependency graph between active Python eggs.
Home-page: http://thomas-lotze.de/en/software/eggdeps/
Author: Thomas Lotze
Author-email: thomas@thomas-lotze.de
License: ZPL 2.1
Keywords: egg eggs dependencies dependency graph tree
Platform: UNKNOWN
Classifier: Development Status :: 3 - Alpha
Classifier: Environment :: Console
Classifier: Intended Audience :: Developers
Classifier: Intended Audience :: System Administrators
Classifier: License :: OSI Approved :: Zope Public License
Classifier: Programming Language :: Python
Classifier: Topic :: Software Development
Classifier: Topic :: Utilities
